usqlh/__init__.py
usqlh/__main__.py
usqlh/cli.py
usqlh/completer.py
usqlh/config.py
usqlh/core.py
usqlh/models.py
usqlh-0.2.0.dist-info/METADATA
usqlh-0.2.0.dist-info/WHEEL
usqlh-0.2.0.dist-info/entry_points.txt
usqlh-0.2.0.dist-info/top_level.txt
usqlh-0.2.0.dist-info/RECORD
