Metadata-Version: 2.4
Name: usqlh
Version: 0.2.0
Summary: CLI tool for managing usql database connections with alias management and Tab auto-completion
Author: usqlh contributors
License: MIT
Project-URL: Homepage, https://github.com/aki-colt/usqlh
Project-URL: Repository, https://github.com/aki-colt/usqlh
Project-URL: Issues, https://github.com/aki-colt/usqlh/issues
Keywords: usql,database,cli,sql,connection-manager
Classifier: Development Status :: 4 - Beta
Classifier: Environment :: Console
Classifier: Intended Audience :: Developers
Classifier: Intended Audience :: System Administrators
Classifier: Topic :: Database
Classifier: Topic :: Utilities
Classifier: License :: OSI Approved :: MIT License
Classifier: Operating System :: OS Independent
Classifier: Programming Language :: Python :: 3
Classifier: Programming Language :: Python :: 3.8
Classifier: Programming Language :: Python :: 3.9
Classifier: Programming Language :: Python :: 3.10
Classifier: Programming Language :: Python :: 3.11
Classifier: Programming Language :: Python :: 3.12
Classifier: Programming Language :: Python :: 3.13
Requires-Python: >=3.8
Provides-Extra: dev
Requires-Dist: ruff>=0.8.0; extra == "dev"
Requires-Dist: mypy>=1.0.0; extra == "dev"
Requires-Dist: pytest>=7.0.0; extra == "dev"
Requires-Dist: pytest-cov>=4.0.0; extra == "dev"
